[
    {
        "title": "Infiniti QX30 2.0 DCT AWD (211 л.с.) 2016",
        "price": "746952",
        "Місто": "Киев",
        "Рік випуску": "2016",
        "Пробіг": "107 тис. км.",
        "Модифікація": "2.0 DCT AWD (211 л.с.)",
        "Кузов": "Кросовер",
        "Колір": "вишневий",
        "Двигун": "Бензиновий / 2.0 л",
        "Коробка": "Робот",
        "Привід": "Повний",
        "VIN": "SJKCH5CP8HA018941"
    },
    {
        "title": "Ford Focus 1.6 TDCi MT (115 л.с.) 2012",
        "price": "314506",
        "Місто": "Снятын",
        "Рік випуску": "2012",
        "Пробіг": "197 тис. км.",
        "Модифікація": "1.6 TDCi MT (115 л.с.)",
        "Кузов": "Універсал",
        "Колір": "синій",
        "Двигун": "Дизельний / 1.6 л",
        "Коробка": "Механіка",
        "Привід": "Передній",
        "VIN": "WF0LXXGCBLCY63939"
    },
    {
        "title": "BMW i5 M60 XDRIVE АТ AWD 81,2 кВт/г (601 л. с.) 2023",
        "price": "Unknown price",
        "Місто": "Киев",
        "Рік випуску": "2023",
        "Пробіг": "1 тис. км.",
        "Модифікація": "M60 XDRIVE АТ AWD 81,2 кВт/г (601 л. с.)",
        "Двигун": "Електричний /",
        "Коробка": "Автомат",
        "Привід": "Повний"
    },
    {
        "title": "BMW X1 25i xDrive 7-Steptronic 4x4 (231 л.с.) 2019",
        "price": "1073253",
        "Місто": "Киев",
        "Рік випуску": "2019",
        "Пробіг": "73 тис. км.",
        "Модифікація": "25i xDrive 7-Steptronic 4x4 (231 л.с.)",
        "Кузов": "Кросовер",
        "Колір": "чорний",
        "Двигун": "Бензиновий / 2.0 л",
        "Коробка": "Автомат",
        "Привід": "Повний",
        "VIN": "WBXJG9C03L3L57517"
    },
    {
        "title": "Mercedes-Benz E-Класс E 400E 2.0  9AT AWD (281 л.с.) 2024",
        "price": "Unknown price",
        "Місто": "Киев",
        "Рік випуску": "2024",
        "Модифікація": "E 400E 2.0  9AT AWD (281 л.с.)",
        "Двигун": "Гібридний / 2.0 куб. см",
        "Коробка": "Автомат",
        "Привід": "Повний"
    },
    {
        "title": "Kia Carens 2016",
        "price": "546454",
        "Місто": "Одесса",
        "Рік випуску": "2016",
        "Пробіг": "219 тис. км.",
        "VIN": "KNAHU814BHK170084"
    },
    {
        "title": "Kia Sorento 2017",
        "price": "876686",
        "Місто": "Одесса",
        "Рік випуску": "2017",
        "Пробіг": "98 тис. км.",
        "VIN": "KNAPS81ABHA297967"
    },
    {
        "title": "Hyundai Accent 2008",
        "price": "216223",
        "Місто": "Одесса",
        "Рік випуску": "2008",
        "Пробіг": "235 тис. км.",
        "VIN": "NLHCM41AP8Z129822"
    },
    {
        "title": "Lexus UX 2022",
        "price": "1316995",
        "Місто": "Одесса",
        "Рік випуску": "2022",
        "Пробіг": "15 тис. км.",
        "VIN": "JTHX3JBHxN2xxxx41"
    },
    {
        "title": "Audi A4 2018",
        "price": "1041802",
        "Місто": "Одесса",
        "Рік випуску": "2018",
        "Пробіг": "112 тис. км.",
        "VIN": "WAUENAF4xJAxxxx57"
    },
    {
        "title": "Audi A4 2011",
        "price": "420652",
        "Місто": "Черкассы",
        "Рік випуску": "2011",
        "Пробіг": "280 тис. км.",
        "VIN": "WAUZZZ8K6CA041543"
    },
    {
        "title": "Nissan Pathfinder 2011",
        "price": "577905",
        "Місто": "Черкассы",
        "Рік випуску": "2011",
        "Пробіг": "281 тис. км.",
        "VIN": "VSKJVWR51U0435160"
    },
    {
        "title": "Mitsubishi Grandis 2008",
        "price": "361682",
        "Місто": "Черкассы",
        "Рік випуску": "2008",
        "Пробіг": "75 тис. км.",
        "VIN": "JMBLRNA4W8Z002725"
    },
    {
        "title": "Volkswagen ID.4 2022",
        "price": "1210849",
        "Місто": "Киев",
        "Рік випуску": "2022",
        "Пробіг": "39 тис. км.",
        "VIN": "LSVUC6E42N2015552"
    },
    {
        "title": "Tesla Model Y 2022",
        "price": "1788755",
        "Місто": "Киев",
        "Рік випуску": "2022",
        "Пробіг": "4 тис. км.",
        "VIN": "7SAYGDEE6PA038046"
    },
    {
        "title": "Renault Master 2012",
        "price": "400995",
        "Місто": "Киев",
        "Рік випуску": "2012",
        "Пробіг": "238 тис. км.",
        "VIN": "VF1MAF4Cx46xxxx14"
    },
    {
        "title": "Volkswagen Golf 2014",
        "price": "483553",
        "Місто": "Киев",
        "Рік випуску": "2014",
        "Пробіг": "152 тис. км.",
        "VIN": "3VW217AUxFMxxxx03"
    },
    {
        "title": "Porsche Panamera 2013",
        "price": "1258025",
        "Місто": "Киев",
        "Рік випуску": "2013",
        "Пробіг": "75 тис. км.",
        "VIN": "WP0ZZZ97xDLxxxx33"
    },
    {
        "title": "Tesla Model 3 2021",
        "price": "978901",
        "Місто": "Киев",
        "Рік випуску": "2021",
        "Пробіг": "37 тис. км.",
        "VIN": "5YJ3E1EA4MF054141"
    },
    {
        "title": "Mercedes-Benz G-Класс 2019",
        "price": "5209012",
        "Місто": "Киев",
        "Рік випуску": "2019",
        "Пробіг": "75 тис. км.",
        "VIN": "WDB46326x1Xxxxx32"
    },
    {
        "title": "BMW X6 2020",
        "price": "2944566",
        "Місто": "Киев",
        "Рік випуску": "2020",
        "Пробіг": "69 тис. км.",
        "VIN": "WBAGT210x09xxxx72"
    },
    {
        "title": "Subaru Legacy 2021",
        "price": "825579",
        "Місто": "Киев",
        "Рік випуску": "2021",
        "Пробіг": "18 тис. км.",
        "VIN": "4S3BWAF6xM3xxxx28"
    },
    {
        "title": "Skoda Octavia 2016",
        "price": "664394",
        "Місто": "Киев",
        "Рік випуску": "2016",
        "Пробіг": "214 тис. км.",
        "VIN": "TMBJJ7NExG0xxxx06"
    },
    {
        "title": "Hyundai Kona Electric 2020",
        "price": "782334",
        "Місто": "Киев",
        "Рік випуску": "2020",
        "Пробіг": "41 тис. км.",
        "VIN": "KMHK281HxLUxxxx94"
    },
    {
        "title": "Ford Fusion 2016",
        "price": "585768",
        "Місто": "Киев",
        "Рік випуску": "2016",
        "Пробіг": "146 тис. км.",
        "VIN": "3FA6P0LUxHRxxxx75"
    }
]