[
    {
        "title": "Volkswagen Multivan 2.0 TDI  DSG 4x4 (204 л.с.)  2020",
        "price": "Unknown price",
        "Місто": "Киев",
        "Рік випуску": "2020",
        "Пробіг": "57 тис. км.",
        "Модифікація": "2.0 TDI  DSG 4x4 (204 л.с.)",
        "Двигун": "Дизельний / 2.0 куб. см",
        "Коробка": "Робот",
        "Привід": "Повний"
    },
    {
        "title": "Nissan Pathfinder 3.5i (284 л.с.) Xtronic CVT 2017",
        "price": "703708",
        "Місто": "Киев",
        "Рік випуску": "2017",
        "Пробіг": "104 тис. км.",
        "Модифікація": "3.5i (284 л.с.) Xtronic CVT",
        "Колір": "білий",
        "Двигун": "Бензиновий / 3.5 л",
        "Коробка": "Варіатор",
        "Привід": "Передній"
    },
    {
        "title": "Hyundai Kona 2021",
        "price": "904205",
        "Місто": "Киев",
        "Рік випуску": "2021",
        "Пробіг": "40 тис. км.",
        "Колір": "червоний"
    },
    {
        "title": "BMW 6 серия 640i 8-Steptronic (320 л.с.) 2018",
        "price": "1725853",
        "Місто": "Ужгород",
        "Рік випуску": "2018",
        "Пробіг": "59 тис. км.",
        "Модифікація": "640i 8-Steptronic (320 л.с.)",
        "Кузов": "Седан",
        "Колір": "сірий",
        "Двигун": "Бензиновий / 3.0 л",
        "Коробка": "Автомат",
        "Привід": "Задній",
        "VIN": "WBA6D0C50KG853107"
    },
    {
        "title": "Mercedes-Benz GLE-Класс 350de  2.0 CDi H АТ 4Matic(320 л.с.) 2023",
        "price": "Unknown price",
        "Місто": "Киев",
        "Рік випуску": "2023",
        "Пробіг": "2 тис. км.",
        "Модифікація": "350de  2.0 CDi H АТ 4Matic(320 л.с.)",
        "Двигун": "Гібридний / 2.0 куб. см",
        "Коробка": "Автомат",
        "Привід": "Повний"
    },
    {
        "title": "Toyota Venza 2021",
        "price": "1517493",
        "Місто": "Киев",
        "Рік випуску": "2021",
        "Пробіг": "42 тис. км.",
        "VIN": "JTEAAAAH3MJ055579"
    },
    {
        "title": "Lamborghini Urus 2020",
        "price": "15725320",
        "Місто": "Киев",
        "Рік випуску": "2020",
        "Пробіг": "24 тис. км.",
        "VIN": "ZPBEA1ZL5LLA09651"
    },
    {
        "title": "Tesla Model 3 2019",
        "price": "1041802",
        "Місто": "Киев",
        "Рік випуску": "2019",
        "Пробіг": "71 тис. км.",
        "VIN": "5YJ3E1EB4KF481518"
    },
    {
        "title": "Hyundai Santa Fe 2013",
        "price": "609356",
        "Місто": "Бердичев",
        "Рік випуску": "2013",
        "Пробіг": "282 тис. км.",
        "VIN": "5XYZUDLB0DG091352"
    },
    {
        "title": "Land Rover Range Rover Evoque 2015",
        "price": "786226",
        "Місто": "Киев",
        "Рік випуску": "2015",
        "Пробіг": "49 тис. км.",
        "VIN": "SALVR2BG7FH074360"
    },
    {
        "title": "Mercedes-Benz E-Класс 2012",
        "price": "483553",
        "Місто": "Киев",
        "Рік випуску": "2012",
        "Пробіг": "121 тис. км.",
        "VIN": "WDD2120411A641352"
    },
    {
        "title": "Toyota Camry 2008",
        "price": "483553",
        "Місто": "Киев",
        "Рік випуску": "2008",
        "Пробіг": "225 тис. км.",
        "VIN": "4T1BK46K49U077653"
    },
    {
        "title": "Volkswagen Polo 2011",
        "price": "294810",
        "Місто": "Киев",
        "Рік випуску": "2011",
        "Пробіг": "183 тис. км.",
        "VIN": "XW8ZZZ61ZCG008333"
    },
    {
        "title": "Kia Forte 2014",
        "price": "389162",
        "Місто": "Киев",
        "Рік випуску": "2014",
        "Пробіг": "145 тис. км.",
        "VIN": "KNAFX4A87F5321527"
    },
    {
        "title": "Skoda Octavia 2004",
        "price": "228017",
        "Місто": "Винница",
        "Рік випуску": "2004",
        "Пробіг": "173 тис. км.",
        "VIN": "TMBJX21U048756996"
    },
    {
        "title": "BMW X3 2015",
        "price": "691914",
        "Місто": "Винница",
        "Рік випуску": "2015",
        "Пробіг": "173 тис. км.",
        "VIN": "5UXWX9C57G0D85599"
    },
    {
        "title": "Peugeot 3008 2015",
        "price": "483553",
        "Місто": "Винница",
        "Рік випуску": "2015",
        "Пробіг": "199 тис. км.",
        "VIN": "VF30UBHZxFSxxxx27"
    },
    {
        "title": "Hyundai ix35 2012",
        "price": "503210",
        "Місто": "Винница",
        "Рік випуску": "2012",
        "Пробіг": "201 тис. км.",
        "VIN": "TMAJU81UxCJxxxx18"
    },
    {
        "title": "Nissan Murano 2016",
        "price": "766609",
        "Місто": "Днепр",
        "Рік випуску": "2016",
        "Пробіг": "47 тис. км.",
        "VIN": "5N1AZ2MH6HN125181"
    },
    {
        "title": "Volvo XC40 2021",
        "price": "1096841",
        "Місто": "Днепр",
        "Рік випуску": "2021",
        "Пробіг": "58 тис. км."
    },
    {
        "title": "Mitsubishi Pajero Wagon 2014",
        "price": "821647",
        "Місто": "Днепр",
        "Рік випуску": "2014",
        "Пробіг": "199 тис. км."
    },
    {
        "title": "Nissan Qashqai 2011",
        "price": "459965",
        "Місто": "Днепр",
        "Рік випуску": "2011",
        "Пробіг": "194 тис. км."
    },
    {
        "title": "Volkswagen Touareg 2013",
        "price": "849167",
        "Місто": "Житомир",
        "Рік випуску": "2013",
        "Пробіг": "179 тис. км.",
        "VIN": "WVGEP9BPXDD011307"
    },
    {
        "title": "Volkswagen Passat 2016",
        "price": "577905",
        "Місто": "Житомир",
        "Рік випуску": "2016",
        "Пробіг": "244 тис. км.",
        "VIN": "WVWZZZ3CZHP006923"
    },
    {
        "title": "Audi Q7 2014",
        "price": "782334",
        "Місто": "Житомир",
        "Рік випуску": "2014",
        "Пробіг": "151 тис. км.",
        "VIN": "WA1LGAFE2ED018611"
    }
]